pycsw/__init__.py
pycsw/oaipmh.py
pycsw/opensearch.py
pycsw/server.py
pycsw/sru.py
pycsw/wsgi.py
pycsw/core/__init__.py
pycsw/core/admin.py
pycsw/core/config.py
pycsw/core/etree.py
pycsw/core/log.py
pycsw/core/metadata.py
pycsw/core/repository.py
pycsw/core/util.py
pycsw/core/formats/__init__.py
pycsw/core/formats/fmt_json.py
pycsw/core/schemas/ogc/cat/csw/3.0/cswAll.xsd
pycsw/core/schemas/ogc/cat/csw/3.0/cswCommon.xsd
pycsw/core/schemas/ogc/cat/csw/3.0/cswGetCapabilities.xsd
pycsw/core/schemas/ogc/cat/csw/3.0/cswGetDomain.xsd
pycsw/core/schemas/ogc/cat/csw/3.0/cswGetRecordById.xsd
pycsw/core/schemas/ogc/cat/csw/3.0/cswGetRecords.xsd
pycsw/core/schemas/ogc/cat/csw/3.0/cswHarvest.xsd
pycsw/core/schemas/ogc/cat/csw/3.0/cswTransaction.xsd
pycsw/core/schemas/ogc/cat/csw/3.0/cswUnHarvest.xsd
pycsw/core/schemas/ogc/cat/csw/3.0/rec-dcmes.xsd
pycsw/core/schemas/ogc/cat/csw/3.0/rec-dcterms.xsd
pycsw/core/schemas/ogc/cat/csw/3.0/record.xsd
pycsw/core/schemas/ogc/csw/2.0.2/CSW-discovery.xsd
pycsw/core/schemas/ogc/csw/2.0.2/CSW-publication.xsd
pycsw/core/schemas/ogc/csw/2.0.2/rec-dcmes.xsd
pycsw/core/schemas/ogc/csw/2.0.2/rec-dcterms.xsd
pycsw/core/schemas/ogc/csw/2.0.2/record.xsd
pycsw/core/schemas/ogc/filter/1.1.0/expr.xsd
pycsw/core/schemas/ogc/filter/1.1.0/filter.xsd
pycsw/core/schemas/ogc/filter/1.1.0/filterCapabilities.xsd
pycsw/core/schemas/ogc/filter/1.1.0/sort.xsd
pycsw/core/schemas/ogc/filter/2.0/expr.xsd
pycsw/core/schemas/ogc/filter/2.0/filter.xsd
pycsw/core/schemas/ogc/filter/2.0/filterAll.xsd
pycsw/core/schemas/ogc/filter/2.0/filterCapabilities.xsd
pycsw/core/schemas/ogc/filter/2.0/query.xsd
pycsw/core/schemas/ogc/filter/2.0/sort.xsd
pycsw/core/schemas/ogc/gml/3.1.1/base/basicTypes.xsd
pycsw/core/schemas/ogc/gml/3.1.1/base/coordinateOperations.xsd
pycsw/core/schemas/ogc/gml/3.1.1/base/coordinateReferenceSystems.xsd
pycsw/core/schemas/ogc/gml/3.1.1/base/coordinateSystems.xsd
pycsw/core/schemas/ogc/gml/3.1.1/base/coverage.xsd
pycsw-2.6.2.dist-info/LICENSE.txt
pycsw-2.6.2.dist-info/METADATA
pycsw-2.6.2.dist-info/WHEEL
pycsw-2.6.2.dist-info/top_level.txt
pycsw-2.6.2.dist-info/RECORD
