Metadata-Version: 2.1
Name: pycsw
Version: 2.6.2
Summary: pycsw is an OGC CSW server implementation written in Python
Home-page: https://pycsw.org/
Author: Tom Kralidis
Author-email: tomkralidis@gmail.com
Maintainer: Tom Kralidis
Maintainer-email: tomkralidis@gmail.com
License: MIT
Keywords: pycsw csw catalogue catalog metadata discovery search ogc iso fgdc dif ebrim inspire
Platform: all
Classifier: Development Status :: 5 - Production/Stable
Classifier: Environment :: Web Environment
Classifier: Intended Audience :: Developers
Classifier: Intended Audience :: Science/Research
Classifier: License :: OSI Approved :: MIT License
Classifier: Operating System :: OS Independent
Classifier: Programming Language :: Python
Classifier: Programming Language :: Python :: 2.7
Classifier: Programming Language :: Python :: 3.4
Classifier: Programming Language :: Python :: 3.5
Classifier: Programming Language :: Python :: 3.6
Classifier: Programming Language :: Python :: 3.7
Classifier: Topic :: Scientific/Engineering :: GIS
License-File: LICENSE.txt
Requires-Dist: geolinks
Requires-Dist: lxml
Requires-Dist: OWSLib<0.29
Requires-Dist: pyproj
Requires-Dist: Shapely
Requires-Dist: xmltodict
